{
  "_meta": {
    "schema_version": "v1",
    "generated_at": "2026-03-17T13:32:51.663820+06:30",
    "cert": "gtq"
  },
  "시험일정": [
    {
      "회차": "제12회",
      "시험명": "2025년 제12회 GTQ/GTQi 정기시험",
      "시험일": "2025-12-27",
      "온라인원서접수표시": "11.26 ~ 12.03",
      "방문접수표시": "12.03 ~ 12.03",
      "수험표공고표시": "12.18 ~ 12.27",
      "성적공고표시": "01.16 ~ 01.23",
      "registerStart": "2025-11-26",
      "registerEnd": "2025-12-03",
      "examDate": "2025-12-27",
      "admitCardStart": "2025-12-18",
      "admitCardEnd": "2025-12-27",
      "resultStart": "2026-01-16",
      "resultEnd": "2026-01-23"
    },
    {
      "회차": "제1회",
      "시험명": "2026년 제1회 GTQ/GTQi/GTQid 정기시험",
      "시험일": "2026-01-24",
      "온라인원서접수표시": "12.24 ~ 12.31",
      "방문접수표시": "12.31 ~ 12.31",
      "수험표공고표시": "01.15 ~ 01.24",
      "성적공고표시": "02.20 ~ 02.27",
      "registerStart": "2026-12-24",
      "registerEnd": "2026-12-31",
      "examDate": "2026-01-24",
      "admitCardStart": "2026-01-15",
      "admitCardEnd": "2026-01-24",
      "resultStart": "2026-02-20",
      "resultEnd": "2026-02-27"
    },
    {
      "회차": "제2회",
      "시험명": "2026년 제2회 GTQ/GTQi 정기시험",
      "시험일": "2026-02-28",
      "온라인원서접수표시": "01.28 ~ 02.04",
      "방문접수표시": "02.04 ~ 02.04",
      "수험표공고표시": "02.19 ~ 02.28",
      "성적공고표시": "03.20 ~ 03.27",
      "registerStart": "2026-01-28",
      "registerEnd": "2026-02-04",
      "examDate": "2026-02-28",
      "admitCardStart": "2026-02-19",
      "admitCardEnd": "2026-02-28",
      "resultStart": "2026-03-20",
      "resultEnd": "2026-03-27"
    },
    {
      "회차": "제3회",
      "시험명": "2026년 제3회 GTQ/GTQi 정기시험",
      "시험일": "2026-03-28",
      "온라인원서접수표시": "02.25 ~ 03.04",
      "방문접수표시": "03.04 ~ 03.04",
      "수험표공고표시": "03.19 ~ 03.28",
      "성적공고표시": "04.17 ~ 04.24",
      "registerStart": "2026-02-25",
      "registerEnd": "2026-03-04",
      "examDate": "2026-03-28",
      "admitCardStart": "2026-03-19",
      "admitCardEnd": "2026-03-28",
      "resultStart": "2026-04-17",
      "resultEnd": "2026-04-24"
    },
    {
      "회차": "제4회",
      "시험명": "2026년 제4회 GTQ/GTQi 정기시험",
      "시험일": "2026-04-25",
      "온라인원서접수표시": "03.25 ~ 04.01",
      "방문접수표시": "04.01 ~ 04.01",
      "수험표공고표시": "04.16 ~ 04.25",
      "성적공고표시": "05.15 ~ 05.22",
      "registerStart": "2026-03-25",
      "registerEnd": "2026-04-01",
      "examDate": "2026-04-25",
      "admitCardStart": "2026-04-16",
      "admitCardEnd": "2026-04-25",
      "resultStart": "2026-05-15",
      "resultEnd": "2026-05-22"
    },
    {
      "회차": "제5회",
      "시험명": "2026년 제5회 GTQ/GTQi/GTQid 정기시험",
      "시험일": "2026-05-30",
      "온라인원서접수표시": "04.29 ~ 05.06",
      "방문접수표시": "05.06 ~ 05.06",
      "수험표공고표시": "05.21 ~ 05.30",
      "성적공고표시": "06.26 ~ 07.03",
      "registerStart": "2026-04-29",
      "registerEnd": "2026-05-06",
      "examDate": "2026-05-30",
      "admitCardStart": "2026-05-21",
      "admitCardEnd": "2026-05-30",
      "resultStart": "2026-06-26",
      "resultEnd": "2026-07-03"
    },
    {
      "회차": "제6회",
      "시험명": "2026년 제6회 GTQ/GTQi 정기시험",
      "시험일": "2026-06-27",
      "온라인원서접수표시": "05.27 ~ 06.04",
      "방문접수표시": "06.04 ~ 06.04",
      "수험표공고표시": "06.18 ~ 06.27",
      "성적공고표시": "07.17 ~ 07.24",
      "registerStart": "2026-05-27",
      "registerEnd": "2026-06-04",
      "examDate": "2026-06-27",
      "admitCardStart": "2026-06-18",
      "admitCardEnd": "2026-06-27",
      "resultStart": "2026-07-17",
      "resultEnd": "2026-07-24"
    },
    {
      "회차": "제7회",
      "시험명": "2026년 제7회 GTQ/GTQi 정기시험",
      "시험일": "2026-07-25",
      "온라인원서접수표시": "06.24 ~ 07.01",
      "방문접수표시": "07.01 ~ 07.01",
      "수험표공고표시": "07.16 ~ 07.25",
      "성적공고표시": "08.14 ~ 08.21",
      "registerStart": "2026-06-24",
      "registerEnd": "2026-07-01",
      "examDate": "2026-07-25",
      "admitCardStart": "2026-07-16",
      "admitCardEnd": "2026-07-25",
      "resultStart": "2026-08-14",
      "resultEnd": "2026-08-21"
    },
    {
      "회차": "제8회",
      "시험명": "2026년 제8회 GTQ/GTQi 정기시험",
      "시험일": "2026-08-22",
      "온라인원서접수표시": "07.22 ~ 07.29",
      "방문접수표시": "07.29 ~ 07.29",
      "수험표공고표시": "08.13 ~ 08.22",
      "성적공고표시": "09.11 ~ 09.18",
      "registerStart": "2026-07-22",
      "registerEnd": "2026-07-29",
      "examDate": "2026-08-22",
      "admitCardStart": "2026-08-13",
      "admitCardEnd": "2026-08-22",
      "resultStart": "2026-09-11",
      "resultEnd": "2026-09-18"
    },
    {
      "회차": "제9회",
      "시험명": "2026년 제9회 GTQ/GTQi/GTQid 정기시험",
      "시험일": "2026-09-19",
      "온라인원서접수표시": "08.19 ~ 08.26",
      "방문접수표시": "08.26 ~ 08.26",
      "수험표공고표시": "09.10 ~ 09.19",
      "성적공고표시": "10.16 ~ 10.23",
      "registerStart": "2026-08-19",
      "registerEnd": "2026-08-26",
      "examDate": "2026-09-19",
      "admitCardStart": "2026-09-10",
      "admitCardEnd": "2026-09-19",
      "resultStart": "2026-10-16",
      "resultEnd": "2026-10-23"
    },
    {
      "회차": "제10회",
      "시험명": "2026년 제10회 GTQ/GTQi 정기시험",
      "시험일": "2026-10-24",
      "온라인원서접수표시": "09.23 ~ 09.30",
      "방문접수표시": "09.30 ~ 09.30",
      "수험표공고표시": "10.15 ~ 10.24",
      "성적공고표시": "11.13 ~ 11.20",
      "registerStart": "2026-09-23",
      "registerEnd": "2026-09-30",
      "examDate": "2026-10-24",
      "admitCardStart": "2026-10-15",
      "admitCardEnd": "2026-10-24",
      "resultStart": "2026-11-13",
      "resultEnd": "2026-11-20"
    },
    {
      "회차": "제11회",
      "시험명": "2026년 제11회 GTQ/GTQi/GTQid 정기시험",
      "시험일": "2026-11-28",
      "온라인원서접수표시": "10.28 ~ 11.04",
      "방문접수표시": "11.04 ~ 11.04",
      "수험표공고표시": "11.19 ~ 11.28",
      "성적공고표시": "12.28 ~ 01.04",
      "registerStart": "2026-10-28",
      "registerEnd": "2026-11-04",
      "examDate": "2026-11-28",
      "admitCardStart": "2026-11-19",
      "admitCardEnd": "2026-11-28",
      "resultStart": "2026-12-28",
      "resultEnd": "2027-01-04"
    },
    {
      "회차": "제12회",
      "시험명": "2026년 제12회 GTQ/GTQi 정기시험",
      "시험일": "2026-12-19",
      "온라인원서접수표시": "11.18 ~ 11.25",
      "방문접수표시": "11.25 ~ 11.25",
      "수험표공고표시": "12.10 ~ 12.19",
      "성적공고표시": "01.08 ~ 01.15",
      "registerStart": "2026-11-18",
      "registerEnd": "2026-11-25",
      "examDate": "2026-12-19",
      "admitCardStart": "2026-12-10",
      "admitCardEnd": "2026-12-19",
      "resultStart": "2027-01-08",
      "resultEnd": "2027-01-15"
    }
  ],
  "시험시간": [
    {
      "교시": "1교시",
      "등급": "1급",
      "입실완료시간": "08:50까지",
      "시험시간표시": "09:00~10:30",
      "start": "09:00",
      "end": "10:30",
      "durationMin": 90,
      "비고": "정기시험기준"
    },
    {
      "교시": "1교시",
      "등급": "2급",
      "입실완료시간": "08:50까지",
      "시험시간표시": "09:00~10:30",
      "start": "09:00",
      "end": "10:30",
      "durationMin": 90,
      "비고": "정기시험기준"
    },
    {
      "교시": "2교시",
      "등급": "1급",
      "입실완료시간": "10:50까지",
      "시험시간표시": "11:00~12:30",
      "start": "11:00",
      "end": "12:30",
      "durationMin": 90,
      "비고": "정기시험기준"
    },
    {
      "교시": "2교시",
      "등급": "2급",
      "입실완료시간": "10:50까지",
      "시험시간표시": "11:00~12:30",
      "start": "11:00",
      "end": "12:30",
      "durationMin": 90,
      "비고": "정기시험기준"
    },
    {
      "교시": "2교시",
      "등급": "3급",
      "입실완료시간": "10:50까지",
      "시험시간표시": "11:00~12:00",
      "start": "11:00",
      "end": "12:00",
      "durationMin": 60,
      "비고": "정기시험기준"
    }
  ],
  "시험내용": {
    "syllabus": [
      {
        "등급": "1급",
        "과목": "GTQ 그래픽기술자격",
        "ext": {
          "kind": "GTQ",
          "title": "그래픽기술자격",
          "문항및시험방법": "4문항 실무작업형 실기시험",
          "시험시간": "90분",
          "swVersion": "Adobe Photoshop CS6, CC(한글, 영문)"
        }
      },
      {
        "등급": "2급",
        "과목": "GTQ 그래픽기술자격",
        "ext": {
          "kind": "GTQ",
          "title": "그래픽기술자격",
          "문항및시험방법": "4문항 실무작업형 실기시험",
          "시험시간": "90분",
          "swVersion": "Adobe Photoshop CS6, CC(한글, 영문)"
        }
      },
      {
        "등급": "3급",
        "과목": "GTQ 그래픽기술자격",
        "ext": {
          "kind": "GTQ",
          "title": "그래픽기술자격",
          "문항및시험방법": "3문항 실무작업형 실기시험",
          "시험시간": "60분",
          "swVersion": "Adobe Photoshop CS6, CC(한글, 영문)"
        }
      },
      {
        "등급": "1급",
        "과목": "GTQi (일러스트)",
        "ext": {
          "kind": "GTQI",
          "title": "일러스트",
          "문항및시험방법": "3문항 실무작업형 실기시험",
          "시험시간": "90분",
          "swVersion": "Adobe Illustrator CS6, CC(영문)"
        }
      },
      {
        "등급": "2급",
        "과목": "GTQi (일러스트)",
        "ext": {
          "kind": "GTQI",
          "title": "일러스트",
          "문항및시험방법": "3문항 실무작업형 실기시험",
          "시험시간": "90분",
          "swVersion": "Adobe Illustrator CS6, CC(영문)"
        }
      },
      {
        "등급": "3급",
        "과목": "GTQi (일러스트)",
        "ext": {
          "kind": "GTQI",
          "title": "일러스트",
          "문항및시험방법": "3문항 실무작업형 실기시험",
          "시험시간": "60분",
          "swVersion": "Adobe Illustrator CS6, CC(영문)"
        }
      },
      {
        "등급": "1급",
        "과목": "GTQid (인디자인)",
        "ext": {
          "kind": "GTQID",
          "title": "인디자인",
          "문항및시험방법": "3문항 실무작업형 실기시험",
          "시험시간": "90분",
          "swVersion": "Adobe InDesign CS6, CC(한글, 영문)"
        }
      },
      {
        "등급": "2급",
        "과목": "GTQid (인디자인)",
        "ext": {
          "kind": "GTQID",
          "title": "인디자인",
          "문항및시험방법": "3문항 실무작업형 실기시험",
          "시험시간": "90분",
          "swVersion": "Adobe InDesign CS6, CC(한글, 영문)"
        }
      }
    ]
  }
}